{
  "leagues": [
    {
      "id": "3918",
      "uid": "s:600~l:3918",
      "name": "English FA Cup",
      "abbreviation": "English FA Cup",
      "midsizeName": "ENG.FA",
      "slug": "eng.fa",
      "season": {
        "year": 2025,
        "startDate": "2025-07-01T04:00Z",
        "endDate": "2026-07-01T03:59Z",
        "displayName": "2025-26 English FA Cup",
        "type": {
          "id": "8",
          "type": 13789,
          "name": "Final",
          "abbreviation": "Final"
        }
      },
      "logos": [
        {
          "href": "https://a.espncdn.com/i/leaguelogos/soccer/500/40.png",
          "width": 500,
          "height": 500,
          "alt": "",
          "rel": [
            "full",
            "default"
          ],
          "lastUpdated": "2019-05-08T16:07Z"
        },
        {
          "href": "https://a.espncdn.com/i/leaguelogos/soccer/500-dark/40.png",
          "width": 500,
          "height": 500,
          "alt": "",
          "rel": [
            "full",
            "dark"
          ],
          "lastUpdated": "2019-05-08T16:07Z"
        }
      ],
      "calendarType": "list",
      "calendarIsWhitelist": true,
      "calendarStartDate": "2025-07-01T04:00Z",
      "calendarEndDate": "2026-07-01T03:59Z",
      "calendar": [
        {
          "label": "English FA Cup",
          "startDate": "2025-07-01T04:00Z",
          "endDate": "2026-07-01T03:59Z",
          "entries": [
            {
              "label": "First Round",
              "detail": "Oct 31-Nov 3",
              "value": "1",
              "startDate": "2025-07-01T07:00Z",
              "endDate": "2025-12-05T07:59Z"
            },
            {
              "label": "Second Round",
              "detail": "Dec 5-8",
              "value": "2",
              "startDate": "2025-12-05T08:00Z",
              "endDate": "2026-01-09T07:59Z"
            },
            {
              "label": "Third Round",
              "detail": "Jan 9-20",
              "value": "3",
              "startDate": "2026-01-09T08:00Z",
              "endDate": "2026-02-13T07:59Z"
            },
            {
              "label": "Fourth Round",
              "detail": "Feb 13-Mar 3",
              "value": "4",
              "startDate": "2026-02-13T08:00Z",
              "endDate": "2026-03-06T07:59Z"
            },
            {
              "label": "Fifth Round",
              "detail": "Mar 6-9",
              "value": "5",
              "startDate": "2026-03-06T08:00Z",
              "endDate": "2026-04-03T06:59Z"
            },
            {
              "label": "Quarterfinals",
              "detail": "Apr 4-5",
              "value": "6",
              "startDate": "2026-04-03T07:00Z",
              "endDate": "2026-04-24T06:59Z"
            },
            {
              "label": "Semifinals",
              "detail": "Apr 25-26",
              "value": "7",
              "startDate": "2026-04-24T07:00Z",
              "endDate": "2026-05-15T06:59Z"
            },
            {
              "label": "Final",
              "detail": "May 16",
              "value": "8",
              "startDate": "2026-05-15T07:00Z",
              "endDate": "2026-07-01T06:59Z"
            }
          ]
        }
      ]
    }
  ],
  "events": [],
  "provider": {
    "id": "100",
    "name": "Draft Kings",
    "displayName": "Draft Kings",
    "priority": 1,
    "logos": [
      {
        "href": "https://a.espncdn.com/i/betting/Draftkings_Light.svg",
        "rel": [
          "light"
        ]
      },
      {
        "href": "https://a.espncdn.com/i/betting/Draftkings_Dark.svg",
        "rel": [
          "dark"
        ]
      }
    ]
  }
}